[{"start": "39.86", "end": "39.96"}, {"start": "41.68", "end": "41.79"}, {"start": "82.82", "end": "82.93"}, {"start": "83.04", "end": "83.14"}, {"start": "88.71", "end": "88.82"}, {"start": "114.86", "end": "115.18"}, {"start": "134.68", "end": "135.0"}, {"start": "166.71", "end": "166.82"}, {"start": "173.79", "end": "173.89"}, {"start": "193.18", "end": "193.39"}, {"start": "195.11", "end": "195.21"}, {"start": "200.79", "end": "200.89"}, {"start": "202.82", "end": "203.25"}, {"start": "209.36", "end": "209.47"}, {"start": "215.79", "end": "216.0"}, {"start": "222.0", "end": "222.32"}, {"start": "228.11", "end": "228.54"}, {"start": "259.18", "end": "259.39"}, {"start": "269.47", "end": "269.68"}, {"start": "271.61", "end": "271.61"}]