[{"start": "8.26", "end": "8.85"}, {"start": "13.27", "end": "13.86"}, {"start": "40.71", "end": "41.89"}, {"start": "42.77", "end": "43.07"}, {"start": "44.25", "end": "45.43"}, {"start": "89.97", "end": "90.86"}, {"start": "94.4", "end": "94.99"}, {"start": "96.17", "end": "99.12"}, {"start": "103.54", "end": "105.01"}, {"start": "110.32", "end": "110.62"}, {"start": "113.86", "end": "114.45"}, {"start": "120.94", "end": "123.89"}, {"start": "144.25", "end": "144.54"}, {"start": "156.05", "end": "156.93"}, {"start": "175.81", "end": "176.11"}, {"start": "180.53", "end": "182.01"}, {"start": "182.89", "end": "183.78"}, {"start": "190.27", "end": "190.86"}, {"start": "195.58", "end": "197.35"}, {"start": "200.0", "end": "206.19"}, {"start": "206.49", "end": "215.04"}, {"start": "232.15", "end": "232.45"}, {"start": "235.1", "end": "235.99"}, {"start": "239.53", "end": "246.61"}, {"start": "247.79", "end": "250.15"}, {"start": "250.44", "end": "251.33"}, {"start": "251.62", "end": "252.51"}, {"start": "258.11", "end": "264.6"}]